claude_statusbar/__init__.py
claude_statusbar/cli.py
claude_statusbar/core.py
claude_statusbar/updater.py
claude_statusbar-1.2.2.dist-info/licenses/LICENSE
claude_statusbar-1.2.2.dist-info/METADATA
claude_statusbar-1.2.2.dist-info/WHEEL
claude_statusbar-1.2.2.dist-info/entry_points.txt
claude_statusbar-1.2.2.dist-info/top_level.txt
claude_statusbar-1.2.2.dist-info/RECORD
