Metadata-Version: 2.4
Name: claude-statusbar
Version: 1.2.2
Summary: Lightweight status bar monitor for Claude AI token usage
Author-email: leeguooooo <leeguooooo@gmail.com>
License: MIT
Project-URL: Homepage, https://github.com/leeguooooo/claude-code-usage-bar
Project-URL: Repository, https://github.com/leeguooooo/claude-code-usage-bar
Project-URL: Issues, https://github.com/leeguooooo/claude-code-usage-bar/issues
Keywords: claude,ai,monitoring,statusbar,token-usage
Classifier: Development Status :: 5 - Production/Stable
Classifier: Intended Audience :: Developers
Classifier: License :: OSI Approved :: MIT License
Classifier: Operating System :: OS Independent
Classifier: Programming Language :: Python :: 3
Classifier: Programming Language :: Python :: 3.9
Classifier: Programming Language :: Python :: 3.10
Classifier: Programming Language :: Python :: 3.11
Classifier: Programming Language :: Python :: 3.12
Classifier: Topic :: Software Development :: Libraries :: Python Modules
Classifier: Topic :: System :: Monitoring
Requires-Python: >=3.9
License-File: LICENSE
Provides-Extra: full
Requires-Dist: claude-monitor>=3.0.0; extra == "full"
Dynamic: license-file
